daring/24.py
daring/AsyncGoogleBatchBackTranslatorFaster.py
daring/AsyncGoogleBatchTranslator.py
daring/AsyncGoogleBatchTranslatorFaster.py
daring/AsyncGoogleBatchTranslatorFasterByWriting.py
daring/AsyncGoogleBatchTranslatorPro.py
daring/GoogleBatchTranslator.py
daring/RSql.py
daring/__init__.py
daring-1.2.0.8.dist-info/LICENSE
daring-1.2.0.8.dist-info/METADATA
daring-1.2.0.8.dist-info/WHEEL
daring-1.2.0.8.dist-info/top_level.txt
daring-1.2.0.8.dist-info/RECORD
