Metadata-Version: 2.1
Name: daring
Version: 1.2.0.8
Summary: The daring is a collection of Python scripts that focuses on providing a range of efficient and flexible translation tool functions. 
Home-page: https://gitee.com/Raodi/daring
Author: Raodi
Author-email: raodi@qq.com
License: UNKNOWN
Platform: UNKNOWN
Classifier: Programming Language :: Python :: 3
Classifier: License :: OSI Approved :: MIT License
Classifier: Operating System :: OS Independent
License-File: LICENSE
